{"expireTime":9007200815030641000,"key":"gatsby-mdx-entire-payload-74cddb4f615c286bcd418b8ef42409d6-","val":{"mdast":{"type":"root","children":[{"type":"paragraph","children":[{"type":"text","value":"Dropdowns are lightweight, JavaScript-powered context menus for housing navigation and actions. They're great for instances where you don't need the full power (and code) of the select menu.","position":{"start":{"line":2,"column":1,"offset":1},"end":{"line":2,"column":191,"offset":191},"indent":[]}}],"position":{"start":{"line":2,"column":1,"offset":1},"end":{"line":2,"column":191,"offset":191},"indent":[]}},{"type":"paragraph","children":[{"type":"text","value":"{:toc}","position":{"start":{"line":4,"column":1,"offset":193},"end":{"line":4,"column":7,"offset":199},"indent":[]}}],"position":{"start":{"line":4,"column":1,"offset":193},"end":{"line":4,"column":7,"offset":199},"indent":[]}},{"type":"heading","depth":2,"children":[{"type":"text","value":"Basic examples","position":{"start":{"line":6,"column":4,"offset":204},"end":{"line":6,"column":18,"offset":218},"indent":[]}}],"position":{"start":{"line":6,"column":1,"offset":201},"end":{"line":6,"column":18,"offset":218},"indent":[]}},{"type":"paragraph","children":[{"type":"text","value":"Dropdowns should be trigged by a ","position":{"start":{"line":8,"column":1,"offset":220},"end":{"line":8,"column":34,"offset":253},"indent":[]}},{"type":"inlineCode","value":"<button>","position":{"start":{"line":8,"column":34,"offset":253},"end":{"line":8,"column":44,"offset":263},"indent":[]}},{"type":"text","value":". ","position":{"start":{"line":8,"column":44,"offset":263},"end":{"line":8,"column":46,"offset":265},"indent":[]}},{"type":"strong","children":[{"type":"link","title":null,"url":"#alignment","children":[{"type":"text","value":"Each dropdown menu requires a directional class","position":{"start":{"line":8,"column":49,"offset":268},"end":{"line":8,"column":96,"offset":315},"indent":[]}}],"position":{"start":{"line":8,"column":48,"offset":267},"end":{"line":8,"column":109,"offset":328},"indent":[]}}],"position":{"start":{"line":8,"column":46,"offset":265},"end":{"line":8,"column":111,"offset":330},"indent":[]}},{"type":"text","value":", much like our tooltips.","position":{"start":{"line":8,"column":111,"offset":330},"end":{"line":8,"column":136,"offset":355},"indent":[]}}],"position":{"start":{"line":8,"column":1,"offset":220},"end":{"line":8,"column":136,"offset":355},"indent":[]}},{"type":"paragraph","children":[{"type":"text","value":"Using a GitHub button:","position":{"start":{"line":10,"column":1,"offset":357},"end":{"line":10,"column":23,"offset":379},"indent":[]}}],"position":{"start":{"line":10,"column":1,"offset":357},"end":{"line":10,"column":23,"offset":379},"indent":[]}},{"type":"code","lang":"html","meta":null,"value":"<details class=\"dropdown details-reset details-overlay d-inline-block\">\n  <summary class=\"btn\" aria-haspopup=\"true\">\n    Dropdown\n    <div class=\"dropdown-caret\"></div>\n  </summary>\n\n  <ul class=\"dropdown-menu dropdown-menu-se\">\n    <li><a class=\"dropdown-item\" href=\"#url\">Dropdown item</a></li>\n    <li><a class=\"dropdown-item\" href=\"#url\">Dropdown item</a></li>\n    <li><a class=\"dropdown-item\" href=\"#url\">Dropdown item</a></li>\n  </ul>\n</details>","position":{"start":{"line":12,"column":1,"offset":381},"end":{"line":25,"column":4,"offset":844},"indent":[1,1,1,1,1,1,1,1,1,1,1,1,1]}},{"type":"paragraph","children":[{"type":"text","value":"Using a button customized with additional utilities:","position":{"start":{"line":27,"column":1,"offset":846},"end":{"line":27,"column":53,"offset":898},"indent":[]}}],"position":{"start":{"line":27,"column":1,"offset":846},"end":{"line":27,"column":53,"offset":898},"indent":[]}},{"type":"code","lang":"html","meta":null,"value":"<details class=\"dropdown details-reset details-overlay d-inline-block\">\n  <summary class=\"text-gray p-2 d-inline\" aria-haspopup=\"true\">\n    Dropdown\n    <div class=\"dropdown-caret\"></div>\n  </summary>\n\n  <ul class=\"dropdown-menu dropdown-menu-se\">\n    <li><a class=\"dropdown-item\" href=\"#url\">Dropdown item</a></li>\n    <li><a class=\"dropdown-item\" href=\"#url\">Dropdown item</a></li>\n    <li><a class=\"dropdown-item\" href=\"#url\">Dropdown item</a></li>\n  </ul>\n</details>","position":{"start":{"line":30,"column":1,"offset":901},"end":{"line":43,"column":4,"offset":1383},"indent":[1,1,1,1,1,1,1,1,1,1,1,1,1]}},{"type":"heading","depth":2,"children":[{"type":"text","value":"Options","position":{"start":{"line":45,"column":4,"offset":1388},"end":{"line":45,"column":11,"offset":1395},"indent":[]}}],"position":{"start":{"line":45,"column":1,"offset":1385},"end":{"line":45,"column":11,"offset":1395},"indent":[]}},{"type":"heading","depth":3,"children":[{"type":"text","value":"Alignment","position":{"start":{"line":47,"column":5,"offset":1401},"end":{"line":47,"column":14,"offset":1410},"indent":[]}}],"position":{"start":{"line":47,"column":1,"offset":1397},"end":{"line":47,"column":14,"offset":1410},"indent":[]}},{"type":"paragraph","children":[{"type":"text","value":"Align the direction of dropdown menus and their arrows with modifier classes.","position":{"start":{"line":49,"column":1,"offset":1412},"end":{"line":49,"column":78,"offset":1489},"indent":[]}}],"position":{"start":{"line":49,"column":1,"offset":1412},"end":{"line":49,"column":78,"offset":1489},"indent":[]}},{"type":"code","lang":"html","meta":null,"value":"<details class=\"dropdown details-reset details-overlay d-inline-block\">\n  <summary class=\"btn\" aria-haspopup=\"true\">\n    .dropdown-ne\n    <div class=\"dropdown-caret\"></div>\n  </summary>\n\n  <ul class=\"dropdown-menu dropdown-menu-ne\">\n    <li><a class=\"dropdown-item\" href=\"#url\">Dropdown item</a></li>\n    <li><a class=\"dropdown-item\" href=\"#url\">Dropdown item</a></li>\n    <li><a class=\"dropdown-item\" href=\"#url\">Dropdown item</a></li>\n  </ul>\n</details>","position":{"start":{"line":51,"column":1,"offset":1491},"end":{"line":64,"column":4,"offset":1958},"indent":[1,1,1,1,1,1,1,1,1,1,1,1,1]}},{"type":"code","lang":"html","meta":null,"value":"<details class=\"dropdown details-reset details-overlay d-inline-block\">\n  <summary class=\"btn\" aria-haspopup=\"true\">\n    .dropdown-e\n    <div class=\"dropdown-caret\"></div>\n  </summary>\n\n  <ul class=\"dropdown-menu dropdown-menu-e\">\n    <li><a class=\"dropdown-item\" href=\"#url\">Dropdown item</a></li>\n    <li><a class=\"dropdown-item\" href=\"#url\">Dropdown item</a></li>\n    <li><a class=\"dropdown-item\" href=\"#url\">Dropdown item</a></li>\n  </ul>\n</details>","position":{"start":{"line":66,"column":1,"offset":1960},"end":{"line":79,"column":4,"offset":2425},"indent":[1,1,1,1,1,1,1,1,1,1,1,1,1]}},{"type":"code","lang":"html","meta":null,"value":"<details class=\"dropdown details-reset details-overlay d-inline-block\">\n  <summary class=\"btn\" aria-haspopup=\"true\">\n    .dropdown-se\n    <div class=\"dropdown-caret\"></div>\n  </summary>\n\n  <ul class=\"dropdown-menu dropdown-menu-se\">\n    <li><a class=\"dropdown-item\" href=\"#url\">Dropdown item</a></li>\n    <li><a class=\"dropdown-item\" href=\"#url\">Dropdown item</a></li>\n    <li><a class=\"dropdown-item\" href=\"#url\">Dropdown item</a></li>\n  </ul>\n</details>","position":{"start":{"line":81,"column":1,"offset":2427},"end":{"line":94,"column":4,"offset":2894},"indent":[1,1,1,1,1,1,1,1,1,1,1,1,1]}},{"type":"code","lang":"html","meta":null,"value":"<details class=\"dropdown details-reset details-overlay d-inline-block\">\n  <summary class=\"btn\" aria-haspopup=\"true\">\n    .dropdown-s\n    <div class=\"dropdown-caret\"></div>\n  </summary>\n\n  <ul class=\"dropdown-menu dropdown-menu-s\">\n    <li><a class=\"dropdown-item\" href=\"#url\">Dropdown item</a></li>\n    <li><a class=\"dropdown-item\" href=\"#url\">Dropdown item</a></li>\n    <li><a class=\"dropdown-item\" href=\"#url\">Dropdown item</a></li>\n  </ul>\n</details>","position":{"start":{"line":96,"column":1,"offset":2896},"end":{"line":109,"column":4,"offset":3361},"indent":[1,1,1,1,1,1,1,1,1,1,1,1,1]}},{"type":"code","lang":"html","meta":null,"value":"<details class=\"dropdown details-reset details-overlay d-inline-block\">\n  <summary class=\"btn\" aria-haspopup=\"true\">\n    .dropdown-sw\n    <div class=\"dropdown-caret\"></div>\n  </summary>\n\n  <ul class=\"dropdown-menu dropdown-menu-sw\">\n    <li><a class=\"dropdown-item\" href=\"#url\">Dropdown item</a></li>\n    <li><a class=\"dropdown-item\" href=\"#url\">Dropdown item</a></li>\n    <li><a class=\"dropdown-item\" href=\"#url\">Dropdown item</a></li>\n  </ul>\n</details>","position":{"start":{"line":111,"column":1,"offset":3363},"end":{"line":124,"column":4,"offset":3830},"indent":[1,1,1,1,1,1,1,1,1,1,1,1,1]}},{"type":"code","lang":"html","meta":null,"value":"<details class=\"dropdown details-reset details-overlay d-inline-block\">\n  <summary class=\"btn\" aria-haspopup=\"true\">\n    .dropdown-w\n    <div class=\"dropdown-caret\"></div>\n  </summary>\n\n  <ul class=\"dropdown-menu dropdown-menu-w\">\n    <li><a class=\"dropdown-item\" href=\"#url\">Dropdown item</a></li>\n    <li><a class=\"dropdown-item\" href=\"#url\">Dropdown item</a></li>\n    <li><a class=\"dropdown-item\" href=\"#url\">Dropdown item</a></li>\n  </ul>\n</details>","position":{"start":{"line":126,"column":1,"offset":3832},"end":{"line":139,"column":4,"offset":4297},"indent":[1,1,1,1,1,1,1,1,1,1,1,1,1]}},{"type":"heading","depth":3,"children":[{"type":"text","value":"Dividers","position":{"start":{"line":141,"column":5,"offset":4303},"end":{"line":141,"column":13,"offset":4311},"indent":[]}}],"position":{"start":{"line":141,"column":1,"offset":4299},"end":{"line":141,"column":13,"offset":4311},"indent":[]}},{"type":"code","lang":"html","meta":null,"value":"<details class=\"dropdown details-reset details-overlay d-inline-block\">\n  <summary class=\"btn\" aria-haspopup=\"true\">\n    Dropdown\n    <div class=\"dropdown-caret\"></div>\n  </summary>\n\n  <ul class=\"dropdown-menu dropdown-menu-se\">\n    <li><a class=\"dropdown-item\" href=\"#url\">Dropdown item</a></li>\n    <li><a class=\"dropdown-item\" href=\"#url\">Dropdown item</a></li>\n    <li><a class=\"dropdown-item\" href=\"#url\">Dropdown item</a></li>\n    <li class=\"dropdown-divider\" role=\"separator\"></li>\n    <li><a class=\"dropdown-item\" href=\"#url\">Another item</a></li>\n    <li><a class=\"dropdown-item\" href=\"#url\">One more</a></li>\n  </ul>\n</details>","position":{"start":{"line":143,"column":1,"offset":4313},"end":{"line":159,"column":4,"offset":4962},"indent":[1,1,1,1,1,1,1,1,1,1,1,1,1,1,1,1]}},{"type":"heading","depth":3,"children":[{"type":"text","value":"Headers","position":{"start":{"line":161,"column":5,"offset":4968},"end":{"line":161,"column":12,"offset":4975},"indent":[]}}],"position":{"start":{"line":161,"column":1,"offset":4964},"end":{"line":161,"column":12,"offset":4975},"indent":[]}},{"type":"code","lang":"html","meta":null,"value":"<details class=\"dropdown details-reset details-overlay d-inline-block\">\n  <summary class=\"btn\" aria-haspopup=\"true\">\n    Dropdown\n    <div class=\"dropdown-caret\"></div>\n  </summary>\n\n  <div class=\"dropdown-menu dropdown-menu-se\">\n    <div class=\"dropdown-header\">\n      Dropdown header\n    </div>\n    <ul>\n      <li><a class=\"dropdown-item\" href=\"#url\">Dropdown item</a></li>\n      <li><a class=\"dropdown-item\" href=\"#url\">Dropdown item</a></li>\n      <li><a class=\"dropdown-item\" href=\"#url\">Dropdown item</a></li>\n    </ul>\n  </div>\n</details>","position":{"start":{"line":163,"column":1,"offset":4977},"end":{"line":181,"column":4,"offset":5534},"indent":[1,1,1,1,1,1,1,1,1,1,1,1,1,1,1,1,1,1]}},{"type":"export","value":"export const _frontmatter = {\"title\":\"Dropdown\",\"path\":\"components/dropdown\",\"status\":\"Stable\",\"source\":\"https://github.com/github/github/tree/master/app/assets/stylesheets/components/dropdown.scss\",\"symbols\":[\"active\",\"anim-scale-in\",\"btn-link\",\"dropdown\",\"dropdown-caret\",\"dropdown-divider\",\"dropdown-header\",\"dropdown-item\",\"dropdown-menu\",\"dropdown-menu-content\",\"dropdown-menu-e\",\"dropdown-menu-ne\",\"dropdown-menu-no-overflow\",\"dropdown-menu-s\",\"dropdown-menu-se\",\"dropdown-menu-sw\",\"dropdown-menu-w\",\"dropdown-signout\",\"octicon\",\"zeroclipboard-is-hover\"]}","position":{"start":{"line":184,"column":1,"offset":5537},"end":{"line":184,"column":562,"offset":6098},"indent":[]}}],"position":{"start":{"line":1,"column":1,"offset":0},"end":{"line":184,"column":562,"offset":6098}}},"scopeImports":[],"scopeIdentifiers":[],"rawMDXOutput":"/* @jsx mdx */\nimport { mdx } from '@mdx-js/react';\n/* @jsx mdx */\n\nexport const _frontmatter = {\"title\":\"Dropdown\",\"path\":\"components/dropdown\",\"status\":\"Stable\",\"source\":\"https://github.com/github/github/tree/master/app/assets/stylesheets/components/dropdown.scss\",\"symbols\":[\"active\",\"anim-scale-in\",\"btn-link\",\"dropdown\",\"dropdown-caret\",\"dropdown-divider\",\"dropdown-header\",\"dropdown-item\",\"dropdown-menu\",\"dropdown-menu-content\",\"dropdown-menu-e\",\"dropdown-menu-ne\",\"dropdown-menu-no-overflow\",\"dropdown-menu-s\",\"dropdown-menu-se\",\"dropdown-menu-sw\",\"dropdown-menu-w\",\"dropdown-signout\",\"octicon\",\"zeroclipboard-is-hover\"]}\nconst makeShortcode = name => function MDXDefaultShortcode(props) {\n  console.warn(\"Component \" + name + \" was not imported, exported, or provided by MDXProvider as global scope\")\n  return <div {...props}/>\n};\n\nconst layoutProps = {\n  _frontmatter\n};\nconst MDXLayout = \"wrapper\"\nexport default function MDXContent({\n  components,\n  ...props\n}) {\n  return <MDXLayout {...layoutProps} {...props} components={components} mdxType=\"MDXLayout\">\n    <p>{`Dropdowns are lightweight, JavaScript-powered context menus for housing navigation and actions. They're great for instances where you don't need the full power (and code) of the select menu.`}</p>\n    <p>{`{:toc}`}</p>\n    <h2>{`Basic examples`}</h2>\n    <p>{`Dropdowns should be trigged by a `}<inlineCode parentName=\"p\">{`<button>`}</inlineCode>{`. `}<strong parentName=\"p\"><a parentName=\"strong\" {...{\n          \"href\": \"#alignment\"\n        }}>{`Each dropdown menu requires a directional class`}</a></strong>{`, much like our tooltips.`}</p>\n    <p>{`Using a GitHub button:`}</p>\n    <pre><code parentName=\"pre\" {...{\n        \"className\": \"language-html\"\n      }}>{`<details class=\"dropdown details-reset details-overlay d-inline-block\">\n  <summary class=\"btn\" aria-haspopup=\"true\">\n    Dropdown\n    <div class=\"dropdown-caret\"></div>\n  </summary>\n\n  <ul class=\"dropdown-menu dropdown-menu-se\">\n    <li><a class=\"dropdown-item\" href=\"#url\">Dropdown item</a></li>\n    <li><a class=\"dropdown-item\" href=\"#url\">Dropdown item</a></li>\n    <li><a class=\"dropdown-item\" href=\"#url\">Dropdown item</a></li>\n  </ul>\n</details>\n`}</code></pre>\n    <p>{`Using a button customized with additional utilities:`}</p>\n    <pre><code parentName=\"pre\" {...{\n        \"className\": \"language-html\"\n      }}>{`<details class=\"dropdown details-reset details-overlay d-inline-block\">\n  <summary class=\"text-gray p-2 d-inline\" aria-haspopup=\"true\">\n    Dropdown\n    <div class=\"dropdown-caret\"></div>\n  </summary>\n\n  <ul class=\"dropdown-menu dropdown-menu-se\">\n    <li><a class=\"dropdown-item\" href=\"#url\">Dropdown item</a></li>\n    <li><a class=\"dropdown-item\" href=\"#url\">Dropdown item</a></li>\n    <li><a class=\"dropdown-item\" href=\"#url\">Dropdown item</a></li>\n  </ul>\n</details>\n`}</code></pre>\n    <h2>{`Options`}</h2>\n    <h3>{`Alignment`}</h3>\n    <p>{`Align the direction of dropdown menus and their arrows with modifier classes.`}</p>\n    <pre><code parentName=\"pre\" {...{\n        \"className\": \"language-html\"\n      }}>{`<details class=\"dropdown details-reset details-overlay d-inline-block\">\n  <summary class=\"btn\" aria-haspopup=\"true\">\n    .dropdown-ne\n    <div class=\"dropdown-caret\"></div>\n  </summary>\n\n  <ul class=\"dropdown-menu dropdown-menu-ne\">\n    <li><a class=\"dropdown-item\" href=\"#url\">Dropdown item</a></li>\n    <li><a class=\"dropdown-item\" href=\"#url\">Dropdown item</a></li>\n    <li><a class=\"dropdown-item\" href=\"#url\">Dropdown item</a></li>\n  </ul>\n</details>\n`}</code></pre>\n    <pre><code parentName=\"pre\" {...{\n        \"className\": \"language-html\"\n      }}>{`<details class=\"dropdown details-reset details-overlay d-inline-block\">\n  <summary class=\"btn\" aria-haspopup=\"true\">\n    .dropdown-e\n    <div class=\"dropdown-caret\"></div>\n  </summary>\n\n  <ul class=\"dropdown-menu dropdown-menu-e\">\n    <li><a class=\"dropdown-item\" href=\"#url\">Dropdown item</a></li>\n    <li><a class=\"dropdown-item\" href=\"#url\">Dropdown item</a></li>\n    <li><a class=\"dropdown-item\" href=\"#url\">Dropdown item</a></li>\n  </ul>\n</details>\n`}</code></pre>\n    <pre><code parentName=\"pre\" {...{\n        \"className\": \"language-html\"\n      }}>{`<details class=\"dropdown details-reset details-overlay d-inline-block\">\n  <summary class=\"btn\" aria-haspopup=\"true\">\n    .dropdown-se\n    <div class=\"dropdown-caret\"></div>\n  </summary>\n\n  <ul class=\"dropdown-menu dropdown-menu-se\">\n    <li><a class=\"dropdown-item\" href=\"#url\">Dropdown item</a></li>\n    <li><a class=\"dropdown-item\" href=\"#url\">Dropdown item</a></li>\n    <li><a class=\"dropdown-item\" href=\"#url\">Dropdown item</a></li>\n  </ul>\n</details>\n`}</code></pre>\n    <pre><code parentName=\"pre\" {...{\n        \"className\": \"language-html\"\n      }}>{`<details class=\"dropdown details-reset details-overlay d-inline-block\">\n  <summary class=\"btn\" aria-haspopup=\"true\">\n    .dropdown-s\n    <div class=\"dropdown-caret\"></div>\n  </summary>\n\n  <ul class=\"dropdown-menu dropdown-menu-s\">\n    <li><a class=\"dropdown-item\" href=\"#url\">Dropdown item</a></li>\n    <li><a class=\"dropdown-item\" href=\"#url\">Dropdown item</a></li>\n    <li><a class=\"dropdown-item\" href=\"#url\">Dropdown item</a></li>\n  </ul>\n</details>\n`}</code></pre>\n    <pre><code parentName=\"pre\" {...{\n        \"className\": \"language-html\"\n      }}>{`<details class=\"dropdown details-reset details-overlay d-inline-block\">\n  <summary class=\"btn\" aria-haspopup=\"true\">\n    .dropdown-sw\n    <div class=\"dropdown-caret\"></div>\n  </summary>\n\n  <ul class=\"dropdown-menu dropdown-menu-sw\">\n    <li><a class=\"dropdown-item\" href=\"#url\">Dropdown item</a></li>\n    <li><a class=\"dropdown-item\" href=\"#url\">Dropdown item</a></li>\n    <li><a class=\"dropdown-item\" href=\"#url\">Dropdown item</a></li>\n  </ul>\n</details>\n`}</code></pre>\n    <pre><code parentName=\"pre\" {...{\n        \"className\": \"language-html\"\n      }}>{`<details class=\"dropdown details-reset details-overlay d-inline-block\">\n  <summary class=\"btn\" aria-haspopup=\"true\">\n    .dropdown-w\n    <div class=\"dropdown-caret\"></div>\n  </summary>\n\n  <ul class=\"dropdown-menu dropdown-menu-w\">\n    <li><a class=\"dropdown-item\" href=\"#url\">Dropdown item</a></li>\n    <li><a class=\"dropdown-item\" href=\"#url\">Dropdown item</a></li>\n    <li><a class=\"dropdown-item\" href=\"#url\">Dropdown item</a></li>\n  </ul>\n</details>\n`}</code></pre>\n    <h3>{`Dividers`}</h3>\n    <pre><code parentName=\"pre\" {...{\n        \"className\": \"language-html\"\n      }}>{`<details class=\"dropdown details-reset details-overlay d-inline-block\">\n  <summary class=\"btn\" aria-haspopup=\"true\">\n    Dropdown\n    <div class=\"dropdown-caret\"></div>\n  </summary>\n\n  <ul class=\"dropdown-menu dropdown-menu-se\">\n    <li><a class=\"dropdown-item\" href=\"#url\">Dropdown item</a></li>\n    <li><a class=\"dropdown-item\" href=\"#url\">Dropdown item</a></li>\n    <li><a class=\"dropdown-item\" href=\"#url\">Dropdown item</a></li>\n    <li class=\"dropdown-divider\" role=\"separator\"></li>\n    <li><a class=\"dropdown-item\" href=\"#url\">Another item</a></li>\n    <li><a class=\"dropdown-item\" href=\"#url\">One more</a></li>\n  </ul>\n</details>\n`}</code></pre>\n    <h3>{`Headers`}</h3>\n    <pre><code parentName=\"pre\" {...{\n        \"className\": \"language-html\"\n      }}>{`<details class=\"dropdown details-reset details-overlay d-inline-block\">\n  <summary class=\"btn\" aria-haspopup=\"true\">\n    Dropdown\n    <div class=\"dropdown-caret\"></div>\n  </summary>\n\n  <div class=\"dropdown-menu dropdown-menu-se\">\n    <div class=\"dropdown-header\">\n      Dropdown header\n    </div>\n    <ul>\n      <li><a class=\"dropdown-item\" href=\"#url\">Dropdown item</a></li>\n      <li><a class=\"dropdown-item\" href=\"#url\">Dropdown item</a></li>\n      <li><a class=\"dropdown-item\" href=\"#url\">Dropdown item</a></li>\n    </ul>\n  </div>\n</details>\n`}</code></pre>\n\n    </MDXLayout>;\n}\n\nMDXContent.isMDXComponent = true;"}}